vessels/__init__.py
vessels/clique.py
vessels/status_1.py
vessels/SSH/command.py
vessels/SSH/connect.py
vessels/SSH/send.py
vessels/_status/status.proc.py
vessels/flask/TV/__init__.py
vessels/flask/gunicorn/__init__.py
vessels/flask/gunicorn/import_custom.py
vessels/flask/gunicorn/process_ID_path.py
vessels/flask/gunicorn/settings.py
vessels/flask/gunicorn/stop.py
vessels/inventory/itemize.py
vessels/proxies/HA/__init__.py
vessels/proxies/HA/__init__v1.py
vessels/proxies/HA/SSL/__init__.py
vessels/proxies/HA/configs/HTTPS_to_HTTP/1.py
vessels/proxies/HA/configs/HTTPS_to_HTTP/__init__.py
vessels/proxies/HA/configs/HTTP_balancer/__init__.py
vessels/proxies/HA/configs/external_reverse/__init__.py
vessels/proxies/HA/install/Fedora/__init__.py
vessels/walls/UFW/__init__.py
vessels-1.0.4.dist-info/METADATA
vessels-1.0.4.dist-info/WHEEL
vessels-1.0.4.dist-info/entry_points.txt
vessels-1.0.4.dist-info/top_level.txt
vessels-1.0.4.dist-info/RECORD
