Metadata-Version: 2.1
Name: vessels
Version: 1.0.4
Summary: flask, gunicorn, HAProxy, etc. tools
Requires-Dist: bracelet
Requires-Dist: shares
Requires-Dist: rich
Requires-Dist: tinydb
Requires-Dist: flask
Requires-Dist: flask-cors
Requires-Dist: flask-limiter
Requires-Dist: flask-socketio
Requires-Dist: gunicorn
Requires-Dist: uvicorn
